pytestmsfabric/__init__.py
pytestmsfabric/nbdownloader.py
pytestmsfabric/nbimport.py
pytestmsfabric/plugin.py
pytestmsfabric/upload.py
pytestmsfabric/utils.py
pytestmsfabric-0.3.7.dist-info/entry_points.txt
pytestmsfabric-0.3.7.dist-info/METADATA
pytestmsfabric-0.3.7.dist-info/WHEEL
pytestmsfabric-0.3.7.dist-info/RECORD
