Metadata-Version: 2.1
Name: pytestmsfabric
Version: 0.3.7
Summary: 
Author: Austin M. Reppert
Author-email: austinmreppert@gmail.com
Requires-Python: >=3.11
Classifier: Framework :: Pytest
Classifier: Programming Language :: Python :: 3
Classifier: Programming Language :: Python :: 3.11
Classifier: Programming Language :: Python :: 3.12
Requires-Dist: asyncio (>=3.4.3,<4.0.0)
Requires-Dist: azure-identity (>=1.17.1,<2.0.0)
Requires-Dist: azure-storage-file-datalake (>=12.16.0,<13.0.0)
Requires-Dist: fabricclientaio (==0.1.0)
Requires-Dist: ipython (>=8.26.0,<9.0.0)
Requires-Dist: nbformat (>=5.10.4,<6.0.0)
Requires-Dist: pyspark (>=3.4.0,<4.0.0)
Requires-Dist: pytest (>=8.2.2,<9.0.0)
